{
  "name": "content_digest",
  "version": "3.1.1",
  "description": {
    "en": "Content Digest",
    "ru": "Дайджест контента",
    "uk": "Дайджест контенту"
  },
  "url": "https://github.com/pytsite/plugin-content_digest",
  "author": {
    "name": "Oleksandr Shepetko",
    "email": "a@shepetko.com",
    "url": "https://shepetko.com"
  },
  "requires": {
    "plugins": [
      "assetman",
      "content>=4.5",
      "font_awesome",
      "form>=4.12",
      "http_api",
      "odm",
      "settings>=1.3"
    ]
  }
}
